airules/api_clients.py
airules/cli.py
airules/commands.py
airules/config.py
airules/exceptions.py
airules/file_operations.py
airules/models.py
airules/py.typed
airules/services.py
airules/ui.py
airules/venv_check.py
airules/analyzer/__init__.py
airules/analyzer/core.py
airules/analyzer/data_models.py
airules/analyzer/dependency_analyzer.py
airules/analyzer/file_scanner.py
airules/analyzer/framework_detector.py
airules/analyzer/language_detector.py
airules/analyzer/models.py
airules/analyzer/package_parser.py
airules/analyzer/tag_generator.py
airules/analyzer/tag_rules.py
airules/analyzer/tag_validator.py
rules4-1.2.3.dist-info/licenses/LICENSE
rules4-1.2.3.dist-info/METADATA
rules4-1.2.3.dist-info/WHEEL
rules4-1.2.3.dist-info/entry_points.txt
rules4-1.2.3.dist-info/top_level.txt
rules4-1.2.3.dist-info/RECORD
