Metadata-Version: 2.4
Name: rules4
Version: 1.2.3
Summary: A universal CLI utility to configure AI rules files for any project.
Author-email: Dimitri Tholen <scriptdude@gmail.com>
License-Expression: MIT
Project-URL: Homepage, https://github.com/dimitritholen/airules
Project-URL: Bug Tracker, https://github.com/dimitritholen/airules/issues
Classifier: Programming Language :: Python :: 3
Classifier: Operating System :: OS Independent
Requires-Python: >=3.7
License-File: LICENSE
Requires-Dist: pytest
Requires-Dist: pytest-cov
Requires-Dist: requests
Requires-Dist: openai
Requires-Dist: anthropic
Requires-Dist: typer[all]
Requires-Dist: rich
Requires-Dist: trio
Dynamic: license-file
